coursemap-0.1.5.dist-info/METADATA
coursemap-0.1.5.dist-info/WHEEL
coursemap-0.1.5.dist-info/entry_points.txt
coursemap-0.1.5.dist-info/licenses/LICENSE
coursemap/__init__.py
coursemap/_core.py
coursemap/_display.py
coursemap/coursemap_rs.cpython-313-darwin.so
coursemap-0.1.5.dist-info/RECORD
