Metadata-Version: 2.4
Name: coursemap
Version: 0.1.5
Classifier: Development Status :: 4 - Beta
Classifier: Intended Audience :: Education
Classifier: Intended Audience :: Developers
Classifier: License :: OSI Approved :: MIT License
Classifier: Programming Language :: Python :: 3
Classifier: Programming Language :: Python :: 3.8
Classifier: Programming Language :: Python :: 3.9
Classifier: Programming Language :: Python :: 3.10
Classifier: Programming Language :: Python :: 3.11
Classifier: Programming Language :: Python :: 3.12
Classifier: Programming Language :: Rust
Classifier: Topic :: Education
Classifier: Topic :: Documentation
Classifier: Topic :: Scientific/Engineering :: Visualization
Requires-Dist: pytest>=6.0 ; extra == 'dev'
Requires-Dist: pytest-cov ; extra == 'dev'
Requires-Dist: black ; extra == 'dev'
Requires-Dist: isort ; extra == 'dev'
Requires-Dist: mypy ; extra == 'dev'
Requires-Dist: pytest>=6.0 ; extra == 'test'
Requires-Dist: pytest-cov ; extra == 'test'
Provides-Extra: dev
Provides-Extra: test
License-File: LICENSE
Summary: A tool to visualize course dependencies from Quarto/Markdown documents
Keywords: quarto,markdown,course,dependency,visualization
Author-email: Kenji Sato <mail@kenjisato.jp>
Requires-Python: >=3.8
Project-URL: Homepage, https://github.com/kenjisato/coursemap
Project-URL: Repository, https://github.com/kenjisato/coursemap
Project-URL: Documentation, https://github.com/kenjisato/coursemap#readme
Project-URL: Issues, https://github.com/kenjisato/coursemap/issues
